brain_games/cli.py
brain_games/games/brain_calc.py
brain_games/games/brain_even.py
brain_games/games/brain_gcd.py
brain_games/games/brain_prime.py
brain_games/games/brain_progression.py
brain_games/init.py
brain_games/launcher.py
brain_games/scripts/brain_calc.py
brain_games/scripts/brain_even.py
brain_games/scripts/brain_games.py
brain_games/scripts/brain_gcd.py
brain_games/scripts/brain_prime.py
brain_games/scripts/brain_progression.py
brain_games/scripts/init.py
sterphius_brain_games-0.1.1.dist-info/WHEEL
sterphius_brain_games-0.1.1.dist-info/entry_points.txt
sterphius_brain_games-0.1.1.dist-info/METADATA
sterphius_brain_games-0.1.1.dist-info/RECORD
