Metadata-Version: 2.1
Name: sterphius-brain-games
Version: 0.1.1
Summary: Brain-games: several terminal games that will allow you to stretch your brain
Home-page: https://github.com/Sterphius/python-project-49
Author: Aleksei Malyshev
Author-email: malyshff@gmail.com
Requires-Python: >=3.11,<4.0
Classifier: Programming Language :: Python :: 3
Classifier: Programming Language :: Python :: 3.11
Requires-Dist: prompt (>=0.4.1,<0.5.0)
Project-URL: Repository, https://github.com/Sterphius/python-project-49
